pymailcheck/__init__.py
pymailcheck-1.0.0.dist-info/DESCRIPTION.rst
pymailcheck-1.0.0.dist-info/METADATA
pymailcheck-1.0.0.dist-info/RECORD
pymailcheck-1.0.0.dist-info/WHEEL
pymailcheck-1.0.0.dist-info/metadata.json
pymailcheck-1.0.0.dist-info/top_level.txt
