Metadata-Version: 2.0
Name: pymailcheck
Version: 1.0.0
Summary: Suggest corrections to user-misspelled email addresses
Home-page: https://github.com/dbarlett/pymailcheck
Author: Dylan Barlett
Author-email: dylan.barlett@gmail.com
License: MIT
Keywords: email mailcheck
Platform: UNKNOWN
Classifier: Development Status :: 4 - Beta
Classifier: Intended Audience :: Developers
Classifier: License :: OSI Approved :: MIT License
Classifier: Programming Language :: Python :: 2.7
Classifier: Programming Language :: Python :: 3.4
Classifier: Topic :: Communications :: Email
